split_git_commit.py
split_git_commit-0.2.0.dist-info/LICENSE
split_git_commit-0.2.0.dist-info/METADATA
split_git_commit-0.2.0.dist-info/WHEEL
split_git_commit-0.2.0.dist-info/entry_points.txt
split_git_commit-0.2.0.dist-info/top_level.txt
split_git_commit-0.2.0.dist-info/RECORD
