Metadata-Version: 2.1
Name: split-git-commit
Version: 0.2.0
Summary: A tool to automatically split large Git commits.
Home-page: https://github.com/alexpizarroj/split-git-commit
Author: Alex Pizarro
Author-email: alex.pizarro.j@gmail.com
License: MIT
Platform: UNKNOWN
Classifier: License :: OSI Approved :: MIT License
Classifier: Programming Language :: Python :: 3
Classifier: Programming Language :: Python :: 3 :: Only
Classifier: Programming Language :: Python :: 3.9
Classifier: Programming Language :: Python :: 3.10
Requires-Python: >=3.9
License-File: LICENSE
Requires-Dist: GitPython (>=3.1.27)
